msaFilesystem/__init__.py
msaFilesystem/msafs.py
msafilesystem-0.0.8.dist-info/METADATA
msafilesystem-0.0.8.dist-info/WHEEL
msafilesystem-0.0.8.dist-info/RECORD
