Metadata-Version: 2.1
Name: msaFilesystem
Version: 0.0.8
Summary: Agnostic Abstract Filesystem API which allows to use S3, GCS, Azure Datalake, your local FS, Youtube etc Optimized for use with FastAPI/Pydantic.
Author: Stefan Welcker
Requires-Python: >=3.9.0,<3.11
Classifier: Programming Language :: Python :: 3
Classifier: Programming Language :: Python :: 3.9
Classifier: Programming Language :: Python :: 3.10
Requires-Dist: autoflake (>=2.0.1,<2.1.0)
Requires-Dist: black (>=22.6.0,<22.7.0)
Requires-Dist: flake8 (>=6.0.0,<6.1.0)
Requires-Dist: fs (==2.4.16)
Requires-Dist: fs-dlk (==0.1.3)
Requires-Dist: fs-dropboxfs (==0.2.2.post2)
Requires-Dist: fs-gcsfs (==1.5.1)
Requires-Dist: fs-googledrivefs (==2.3.2)
Requires-Dist: fs-onedrivefs (==1.1.4)
Requires-Dist: fs-s3fs (==1.1.1)
Requires-Dist: fs-smbfs (==1.0.7)
Requires-Dist: fs-webdavfs (==0.4.2)
Requires-Dist: fs-youtube (==0.3.1)
Requires-Dist: isort (>=5.12.0,<5.13.0)
Requires-Dist: loguru (==0.6.0)
Requires-Dist: multidict (>=6.0.4,<6.1.0)
Requires-Dist: mypy (>=1.0.0,<1.1.0)
Requires-Dist: pydantic (==1.9.2)
Requires-Dist: pysmb (==1.2.8)
Requires-Dist: python-dotenv (==0.20.0)
Requires-Dist: regex (==2022.3.15)
Requires-Dist: setuptools (>=67.6.1,<67.7.0)
Requires-Dist: six (==1.16.0)
Requires-Dist: twine (==4.0.1)
